{
  "status": "ok",
  "expert_name": "海天",
  "lottery_name": "超级大乐透",
  "issue_no": "26033",
  "used_sources": [
    "内嵌 skill_md",
    "内嵌 replay_md",
    "内嵌 snapshot_support_md",
    "C:\\Users\\ADMINI~1\\AppData\\Local\\Temp\\supser-predict-ea5bb9qb\\workspace\\snapshot-support.json"
  ],
  "missing_or_uncertain": [],
  "markdown": "# 海天_超级大乐透_26033\n\n## 数据快照\n- 统计时间：2026-03-29；最新开奖期号：26032；目标期号：26033。\n- 上期开奖：26032期开出03、04、19、26、32+01、12。前区和值84，跨度29，奇偶比2:3，大小比2:3；后区和值13，跨度11。\n- 最近10期前区三区累计为19:10:21，前一区和前三区偏活跃，前二区偏冷。\n- 前区高遗漏前列：07(31)、20(25)、31(13)、01(12)、23(12)、14(11)、18(10)。\n- 后区冷热分层：冷码02、04、06；温码03、08、09、10、11；热码01、05、07、12。\n- `replay.md` 的26023-26032期样本显示，海天固定采用“上期开奖 -> 前一区 -> 前二区 -> 前三区 -> 后区 -> 前区15码/11码/8码 -> 后区5码/3码 -> 单注”的压缩链。\n- `snapshot-support.json` 的 `currentTransitionSnapshot` 显示，26032期后前区跟随热度集中在08、22、28、31、34一带，后区对01+12组合的后续热度偏向05、02、07，冷向防04、06。\n\n## 执行核对\n1. 已按上期开奖先交代26032期前区和值、跨度、奇偶比、大小比，以及后区和值、跨度。\n2. 已按前一区【01-12】统计最近10期总出号、已开号、未开号和高遗漏号，并判断本期区间节奏。\n3. 已按前二区【13-23】结合热冷与遗漏做压缩，并落到精选2码。\n4. 已按前三区【24-35】结合活跃度与高遗漏回补需求给出大范围和精选3胆。\n5. 已按后区冷热遗漏三层法拆分冷码、温码、热码，并判断主防方向。\n6. 已在三区判断后给出前区大底15码。\n7. 已按同一逻辑把15码继续压缩成前区缩水11码和前区精选8码。\n8. 已给出后区大底5码、后区3码参考，并与前区精选8码收束到单注参考。\n\n## 按技能步骤执行\n上期开奖：大乐透第26032期开出奖号03、04、19、26、32+01、12。前区和值84，跨度29，奇偶比2:3，大小比2:3。后区和值13，跨度11。\n\n前一区【01-12】：上期该区开出2个奖号03、04。最近10期该区出现19个奖号，表现依旧活跃，其中开出号码02、03、04、05、06、08、09、10、11、12，未出号码01、07。当前07遗漏31期居首，01遗漏12期，低位区有补位需求；结合26032期后的条件转移，08、09、10、12仍有热度支撑。本期看好该区走温，出现1-2个奖号，关注号码：07、08、09、10、11、12。\n\n前二区【13-23】：上期该区开出1个号码19。最近10期该区开出10个号码，整体明显偏冷，其中出现奖号13、15、16、17、19、21、22，未出奖号14、18、20、23。20遗漏25期，23遗漏12期，14遗漏11期，18遗漏10期，冷势积压较重；再看26032期后的条件转移，22具备连续热度，16也有跟随支撑。本期预计该区走温，在2个以内出号，注意号码：14、16、20、22、23，精选2码：20、22。\n\n前三区【24-35】：上期该区开出2个奖号26、32。最近10期该区出现21个奖号，走势活跃，其中号码24、25、26、27、28、29、30、32、33、34、35已经出现，号码31近10期未开且遗漏13期，25遗漏9期，24遗漏7期。结合26032期后的条件转移，25、28、31、34一带支撑较强，高位区仍有继续出号和回补空间。本期注意该区走热，大范围看好：24、25、28、30、31、34，精选3胆：28、31、34。\n\n后区分析：上期开出奖号01、12，后区和值13，跨度11。目前遗漏值较大的冷码有3个：02、04、06，分别遗漏21期、11期、10期；遗漏值4-9之间的温码有5个：03、08、09、10、11；遗漏值较小的热码有4个：01、05、07、12。结合26032期后01+12的条件转移，05、02、07的后续热度更强，本期后区防1个冷码配1个热码，看好两码02、07。\n\n前区大底15码：07 08 09 10 11 12 14 16 20 22 24 25 28 31 34\n\n前区缩水11码：07 08 09 10 12 20 22 25 28 31 34\n\n前区精选8码：07 08 10 20 22 28 31 34\n\n后区大底5码：02 04 05 07 08\n\n后区3码参考：02 05 07\n\n单注参考：08 10 22 28 31 + 02 07\n\n## 最终推荐结果\n- 前区大底15码：07 08 09 10 11 12 14 16 20 22 24 25 28 31 34\n- 前区缩水11码：07 08 09 10 12 20 22 25 28 31 34\n- 前区精选8码：07 08 10 20 22 28 31 34\n- 后区大底5码：02 04 05 07 08\n- 后区3码参考：02 05 07\n- 单注参考：08 10 22 28 31 + 02 07\n\n## 风险与问题\n\n- 未发现会影响本期完整输出的明显本地数据缺口或方法阻断。\n- 彩票结果具有随机性，方法复刻不等于结果保证。\n\n"
}